{
    "siteType": "HOME",
    "title": "Darkholes",
    "title-lead": "Lorem ipsum dolor sit amet, consectetur adipiscing elit, sed do eiusmod tempor incididunt ut labore et dolore magna aliqua.",
    "title-logo": "https://raw.githubusercontent.com/purdynerdy/artpics/master/logo/logo.png",
    "primary-background": "white",
    "secondary-background": "#000",
    "on-air-id": "darkholes",
    "social": [
        {
            "name": "Shop",
            "link": "https://holes.darkowlzz.space",
            "image": ""
        },
        {
            "name": "Instagram",
            "link": "",
            "image": ""
        },
        {
            "name": "Twitter",
            "link": "",
            "image": ""
        },
        {
            "name": "Twitch",
            "link": "",
            "image": ""
        },
        {
            "name": "Periscope",
            "link": "",
            "image": ""
        }
    ],
    "info": [
        {
            "title": "Other Pages",
            "items": [
                {
                    "name": "Gaming",
                    "link": ""
                },
                {
                    "name": "Music",
                    "link": ""
                },
                {
                    "name": "Books",
                    "link": ""
                },
                {
                    "name": "Thoughts",
                    "link": ""
                }
            ]
        },
        {
            "title": "Resources",
            "items": [
                {
                    "name": "Twitter",
                    "link": ""
                },
                {
                    "name": "Discord",
                    "link": ""
                },
                {
                    "name": "Twitch",
                    "link": ""
                }
            ]
        },
        {
            "title": "About",
            "items": [
                {
                    "name": "Privacy",
                    "link": ""
                },
                {
                    "name": "Terms",
                    "link": ""
                }
            ]
        }
    ]
}
